{
  "purchase_comic": [
    {
      "id": 1,
      "title": "BTC/JPY",
      "copyright": "13,584,396円",
      "expiration_date": "+1.13%",
      "catchcopy": "ビットコイン"
    },
    {
      "id": 2,
      "title": "ETH/JPY",
      "copyright": "500,914円",
      "expiration_date": "-1.48%",
      "catchcopy": "イーサリアム"
    },
    {
      "id": 3,
      "title": "XRP/JPY",
      "copyright": "112.68円",
      "expiration_date": "+20.95%",
      "catchcopy": "リップル（XRP）"
    },
    {
      "id": 4,
      "title": "SHIB/JPY",
      "copyright": "0.0040441円",
      "expiration_date": "-1.79%",
      "catchcopy": "シバイヌ"
    },
    {
      "id": 5,
      "title": "POL/JPY",
      "copyright": "61.75円",
      "expiration_date": "-3.94%",
      "catchcopy": "ポリゴンエコシステムトークン"
    },
    {
      "id": 6,
      "title": "MATIC/JPY",
      "copyright": "61.95円",
      "expiration_date": "-3.94%",
      "catchcopy": "ポリゴン"
    },
    {
      "id": 7,
      "title": "DOGE/JPY",
      "copyright": "57.42円",
      "expiration_date": "+12.57%",
      "catchcopy": "ドージコイン"
    },
    {
      "id": 8,
      "title": "AVAX/JPY",
      "copyright": "5,241円",
      "expiration_date": "-1.61%",
      "catchcopy": "アバランチ"
    },
    {
      "id": 9,
      "title": "BCH/JPY",
      "copyright": "67,274円",
      "expiration_date": "-5.21%",
      "catchcopy": "ビットコインキャッシュ"
    },
    {
      "id": 10,
      "title": "DOT/JPY",
      "copyright": "823円",
      "expiration_date": "-3.29%",
      "catchcopy": "ポルカドット"
    },
    {
      "id": 11,
      "title": "LINK/JPY",
      "copyright": "2,163円",
      "expiration_date": "-3.44%",
      "catchcopy": "チェーンリンク"
    },
    {
      "id": 12,
      "title": "LTC/JPY",
      "copyright": "11,908円",
      "expiration_date": "-1.23%",
      "catchcopy": "ライトコイン"
    },
    {
      "id": 13,
      "title": "XLM/JPY",
      "copyright": "21.335円",
      "expiration_date": "+23.62%",
      "catchcopy": "ステラルーメン"
    },
    {
      "id": 14,
      "title": "ETC/JPY",
      "copyright": "3,542円",
      "expiration_date": "-2.69%",
      "catchcopy": "イーサリアムクラシック"
    },
    {
      "id": 15,
      "title": "MKR/JPY",
      "copyright": "235,446.40円",
      "expiration_date": "+1.38%",
      "catchcopy": "メイカー"
    },
    {
      "id": 16,
      "title": "IMX/JPY",
      "copyright": "208.9円",
      "expiration_date": "-0.33%",
      "catchcopy": "イミュータブル"
    },
    {
      "id": 17,
      "title": "RNDR/JPY",
      "copyright": "1,095.2円",
      "expiration_date": "+6.26%",
      "catchcopy": "レンダートークン"
    },
    {
      "id": 18,
      "title": "GRT/JPY",
      "copyright": "29.44円",
      "expiration_date": "-0.67%",
      "catchcopy": "ザ・グラフ"
    },
    {
      "id": 19,
      "title": "AXS/JPY",
      "copyright": "848円",
      "expiration_date": "-2.86%",
      "catchcopy": "アクシーインフィニティ"
    },
    {
      "id": 20,
      "title": "XTZ/JPY",
      "copyright": "115.3円",
      "expiration_date": "+1.59%",
      "catchcopy": "テゾス"
    },
    {
      "id": 21,
      "title": "FLR/JPY",
      "copyright": "2.375円",
      "expiration_date": "+5.93%",
      "catchcopy": "フレア"
    },
    {
      "id": 22,
      "title": "SAND/JPY",
      "copyright": "46.60円",
      "expiration_date": "+1.64%",
      "catchcopy": "ザ・サンドボックス"
    },
    {
      "id": 23,
      "title": "MANA/JPY",
      "copyright": "55.86円",
      "expiration_date": "+2.20%",
      "catchcopy": "ディセントラランド"
    },
    {
      "id": 24,
      "title": "CHZ/JPY",
      "copyright": "10.55円",
      "expiration_date": "-1.40%",
      "catchcopy": "チリーズ"
    },
    {
      "id": 25,
      "title": "APE/JPY",
      "copyright": "172.9円",
      "expiration_date": "-1.98%",
      "catchcopy": "エイプコイン"
    },
    {
      "id": 26,
      "title": "BAT/JPY",
      "copyright": "30.72円",
      "expiration_date": "+3.78%",
      "catchcopy": "ベーシックアテンショントークン"
    },
    {
      "id": 27,
      "title": "MASK/JPY",
      "copyright": "490.3円",
      "expiration_date": "+6.63%",
      "catchcopy": "マスクネットワーク"
    },
    {
      "id": 28,
      "title": "XEM/JPY",
      "copyright": "3.049円",
      "expiration_date": "+8.24%",
      "catchcopy": "ネム"
    },
    {
      "id": 29,
      "title": "LSK/JPY",
      "copyright": "153.5円",
      "expiration_date": "+7.95%",
      "catchcopy": "リスク"
    },
    {
      "id": 30,
      "title": "XYM/JPY",
      "copyright": "2.00円",
      "expiration_date": "-1.96%",
      "catchcopy": "シンボル"
    },
    {
      "id": 31,
      "title": "MONA/JPY",
      "copyright": "42.300円",
      "expiration_date": "-1.51%",
      "catchcopy": "モナコイン"
    },
    {
      "id": 32,
      "title": "PLT/JPY",
      "copyright": "6.20円",
      "expiration_date": "-6.63%",
      "catchcopy": "パレットトークン"
    },
    {
      "id": 33,
      "title": "DAI/JPY",
      "copyright": "154.8円",
      "expiration_date": "+0.78%",
      "catchcopy": "ダイ"
    },
    {
      "id": 34,
      "title": "ZPG/JPY",
      "copyright": "12,936.50円",
      "expiration_date": "-0.14%",
      "catchcopy": "ジパングコイン"
    },
    {
      "id": 35,
      "title": "ZPGAG/JPY",
      "copyright": "152.8円",
      "expiration_date": "+0.86%",
      "catchcopy": "ジパングコインシルバー"
    },
    {
      "id": 36,
      "title": "ZPGPT/JPY",
      "copyright": "4,717円",
      "expiration_date": "-0.94%",
      "catchcopy": "ジパングコインプラチナ"
    }
  ]
}