{
  "purchase_comic": [
    {
      "id": 1,
      "title": "BTC/JPY",
      "copyright": "10,156,840円",
      "expiration_date": "-1.60%",
      "catchcopy": "ビットコイン"
    },
    {
      "id": 2,
      "title": "ETH/JPY",
      "copyright": "286,139円",
      "expiration_date": "-1.24%",
      "catchcopy": "イーサリアム"
    },
    {
      "id": 3,
      "title": "XRP/JPY",
      "copyright": "179.32円",
      "expiration_date": "-1.59%",
      "catchcopy": "エックスアールピー（XRP）"
    },
    {
      "id": 4,
      "title": "SOL/JPY",
      "copyright": "12,741円",
      "expiration_date": "-2.08%",
      "catchcopy": "ソラナ"
    },
    {
      "id": 5,
      "title": "DOGE/JPY",
      "copyright": "11.82円",
      "expiration_date": "-1.50%",
      "catchcopy": "ドージコイン"
    },
    {
      "id": 6,
      "title": "SHIB/JPY",
      "copyright": "0.0006949円",
      "expiration_date": "-2.18%",
      "catchcopy": "シバイヌ"
    },
    {
      "id": 7,
      "title": "PEPE/JPY",
      "copyright": "0.000427円",
      "expiration_date": "-2.06%",
      "catchcopy": "ペペ"
    },
    {
      "id": 8,
      "title": "XLM/JPY",
      "copyright": "29.598円",
      "expiration_date": "-3.49%",
      "catchcopy": "ステラルーメン"
    },
    {
      "id": 9,
      "title": "LINK/JPY",
      "copyright": "1,251円",
      "expiration_date": "-1.81%",
      "catchcopy": "チェーンリンク"
    },
    {
      "id": 10,
      "title": "AVAX/JPY",
      "copyright": "1,060円",
      "expiration_date": "-1.49%",
      "catchcopy": "アバランチ"
    },
    {
      "id": 11,
      "title": "BCH/JPY",
      "copyright": "38,251円",
      "expiration_date": "-1.79%",
      "catchcopy": "ビットコインキャッシュ"
    },
    {
      "id": 12,
      "title": "LTC/JPY",
      "copyright": "7,165円",
      "expiration_date": "-1.55%",
      "catchcopy": "ライトコイン"
    },
    {
      "id": 13,
      "title": "DOT/JPY",
      "copyright": "136円",
      "expiration_date": "-1.45%",
      "catchcopy": "ポルカドット"
    },
    {
      "id": 14,
      "title": "ETC/JPY",
      "copyright": "1,136円",
      "expiration_date": "-0.18%",
      "catchcopy": "イーサリアムクラシック"
    },
    {
      "id": 15,
      "title": "POL/JPY",
      "copyright": "12.50円",
      "expiration_date": "-0.64%",
      "catchcopy": "ポリゴンエコシステムトークン"
    },
    {
      "id": 16,
      "title": "MATIC/JPY",
      "copyright": "13.14円",
      "expiration_date": "0.00%",
      "catchcopy": "ポリゴン"
    },
    {
      "id": 17,
      "title": "SKY/JPY",
      "copyright": "9.01円",
      "expiration_date": "+2.62%",
      "catchcopy": "スカイ"
    },
    {
      "id": 18,
      "title": "MKR/JPY",
      "copyright": "204,387.28円",
      "expiration_date": "+2.50%",
      "catchcopy": "メイカー"
    },
    {
      "id": 19,
      "title": "RNDR/JPY",
      "copyright": "266.1円",
      "expiration_date": "-1.30%",
      "catchcopy": "レンダートークン"
    },
    {
      "id": 20,
      "title": "FLR/JPY",
      "copyright": "1.069円",
      "expiration_date": "-2.11%",
      "catchcopy": "フレア"
    },
    {
      "id": 21,
      "title": "IMX/JPY",
      "copyright": "23.0円",
      "expiration_date": "+2.22%",
      "catchcopy": "イミュータブル"
    },
    {
      "id": 22,
      "title": "GRT/JPY",
      "copyright": "2.88円",
      "expiration_date": "-1.37%",
      "catchcopy": "ザ・グラフ"
    },
    {
      "id": 23,
      "title": "XTZ/JPY",
      "copyright": "39.2円",
      "expiration_date": "-6.22%",
      "catchcopy": "テゾス"
    },
    {
      "id": 24,
      "title": "SAND/JPY",
      "copyright": "7.93円",
      "expiration_date": "+0.38%",
      "catchcopy": "ザ・サンドボックス"
    },
    {
      "id": 25,
      "title": "MANA/JPY",
      "copyright": "12.15円",
      "expiration_date": "+8.10%",
      "catchcopy": "ディセントラランド"
    },
    {
      "id": 26,
      "title": "APE/JPY",
      "copyright": "26.1円",
      "expiration_date": "+11.54%",
      "catchcopy": "エイプコイン"
    },
    {
      "id": 27,
      "title": "AXS/JPY",
      "copyright": "163円",
      "expiration_date": "+1.88%",
      "catchcopy": "アクシーインフィニティ"
    },
    {
      "id": 28,
      "title": "CHZ/JPY",
      "copyright": "2.80円",
      "expiration_date": "-0.71%",
      "catchcopy": "チリーズ"
    },
    {
      "id": 29,
      "title": "BAT/JPY",
      "copyright": "13.74円",
      "expiration_date": "-1.72%",
      "catchcopy": "ベーシックアテンショントークン"
    },
    {
      "id": 30,
      "title": "MASK/JPY",
      "copyright": "68.8円",
      "expiration_date": "+1.93%",
      "catchcopy": "マスクネットワーク"
    },
    {
      "id": 31,
      "title": "LSK/JPY",
      "copyright": "14.3円",
      "expiration_date": "+2.14%",
      "catchcopy": "リスク"
    },
    {
      "id": 32,
      "title": "XYM/JPY",
      "copyright": "0.50円",
      "expiration_date": "0.00%",
      "catchcopy": "シンボル"
    },
    {
      "id": 33,
      "title": "XEM/JPY",
      "copyright": "0.106円",
      "expiration_date": "+35.90%",
      "catchcopy": "ネム"
    },
    {
      "id": 34,
      "title": "MONA/JPY",
      "copyright": "10.574円",
      "expiration_date": "-3.40%",
      "catchcopy": "モナコイン"
    },
    {
      "id": 35,
      "title": "PLT/JPY",
      "copyright": "0.37円",
      "expiration_date": "0.00%",
      "catchcopy": "パレットトークン"
    },
    {
      "id": 36,
      "title": "DAI/JPY",
      "copyright": "162.6円",
      "expiration_date": "+0.12%",
      "catchcopy": "ダイ"
    },
    {
      "id": 37,
      "title": "ZPG/JPY",
      "copyright": "21,293.50円",
      "expiration_date": "-0.64%",
      "catchcopy": "ジパングコイン"
    },
    {
      "id": 38,
      "title": "ZPGAG/JPY",
      "copyright": "303.8円",
      "expiration_date": "-2.78%",
      "catchcopy": "ジパングコインシルバー"
    },
    {
      "id": 39,
      "title": "ZPGPT/JPY",
      "copyright": "8,325円",
      "expiration_date": "-1.97%",
      "catchcopy": "ジパングコインプラチナ"
    }
  ]
}