{
  "purchase_comic": [
    {
      "id": 1,
      "title": "USD",
      "copyright": "153.54",
      "expiration_date": "151.54",
      "expiration_date_text": "152.54",
      "catchcopy": "米ドル"
    },
    {
      "id": 2,
      "title": "GBP",
      "copyright": "207.63",
      "expiration_date": "199.63",
      "expiration_date_text": "203.63",
      "catchcopy": "英ポンド"
    },
    {
      "id": 3,
      "title": "EUR",
      "copyright": "179.25",
      "expiration_date": "176.25",
      "expiration_date_text": "177.75",
      "catchcopy": "ユーロ"
    },
    {
      "id": 4,
      "title": "CAD",
      "copyright": "110.66",
      "expiration_date": "107.46",
      "expiration_date_text": "109.06",
      "catchcopy": "カナダドル"
    },
    {
      "id": 5,
      "title": "CHF",
      "copyright": "192.92",
      "expiration_date": "191.12",
      "expiration_date_text": "192.02",
      "catchcopy": "スイスフラン"
    },
    {
      "id": 6,
      "title": "SEK",
      "copyright": "16.67",
      "expiration_date": "15.87",
      "expiration_date_text": "16.27",
      "catchcopy": "スウェーデンクローネ"
    },
    {
      "id": 7,
      "title": "DKK",
      "copyright": "24.10",
      "expiration_date": "23.50",
      "expiration_date_text": "23.80",
      "catchcopy": "デンマーククローネ"
    },
    {
      "id": 8,
      "title": "NOK",
      "copyright": "15.58",
      "expiration_date": "14.98",
      "expiration_date_text": "15.28",
      "catchcopy": "ノルウェークローネ"
    },
    {
      "id": 9,
      "title": "AUD",
      "copyright": "102.54",
      "expiration_date": "97.54",
      "expiration_date_text": "100.04",
      "catchcopy": "オーストラリアドル"
    },
    {
      "id": 10,
      "title": "NZD",
      "copyright": "90.69",
      "expiration_date": "85.59",
      "expiration_date_text": "88.14",
      "catchcopy": "ニュージーランドドル"
    },
    {
      "id": 11,
      "title": "ZAR",
      "copyright": "11.35",
      "expiration_date": "6.35",
      "expiration_date_text": "8.85",
      "catchcopy": "南アフリカランド"
    },
    {
      "id": 12,
      "title": "BHD",
      "copyright": "412.62",
      "expiration_date": "396.62",
      "expiration_date_text": "404.62",
      "catchcopy": "バーレーンディナール"
    },
    {
      "id": 13,
      "title": "IDR(100)",
      "copyright": "*****",
      "expiration_date": "*****",
      "expiration_date_text": "*****",
      "catchcopy": "インドネシアルピア"
    },
    {
      "id": 14,
      "title": "CNY",
      "copyright": "21.77",
      "expiration_date": "21.17",
      "expiration_date_text": "21.47",
      "catchcopy": "中国人民元"
    },
    {
      "id": 15,
      "title": "HKD",
      "copyright": "20.07",
      "expiration_date": "19.21",
      "expiration_date_text": "19.64",
      "catchcopy": "香港ドル"
    },
    {
      "id": 16,
      "title": "INR",
      "copyright": "2.10",
      "expiration_date": "*****",
      "expiration_date_text": "1.73",
      "catchcopy": "インドルピー"
    },
    {
      "id": 17,
      "title": "MYR",
      "copyright": "*****",
      "expiration_date": "*****",
      "expiration_date_text": "*****",
      "catchcopy": "マレーシアリンギ"
    },
    {
      "id": 18,
      "title": "PHP",
      "copyright": "2.71",
      "expiration_date": "*****",
      "expiration_date_text": "2.59",
      "catchcopy": "フィリピンペソ"
    },
    {
      "id": 19,
      "title": "SGD",
      "copyright": "118.55",
      "expiration_date": "116.89",
      "expiration_date_text": "117.72",
      "catchcopy": "シンガポールドル"
    },
    {
      "id": 20,
      "title": "KRW(100)",
      "copyright": "*****",
      "expiration_date": "*****",
      "expiration_date_text": "*****",
      "catchcopy": "韓国ウォン"
    },
    {
      "id": 21,
      "title": "THB",
      "copyright": "4.75",
      "expiration_date": "4.59",
      "expiration_date_text": "4.67",
      "catchcopy": "タイバーツ"
    },
    {
      "id": 22,
      "title": "KWD",
      "copyright": "505.20",
      "expiration_date": "489.20",
      "expiration_date_text": "497.20",
      "catchcopy": "クウェートディナール"
    },
    {
      "id": 23,
      "title": "SAR",
      "copyright": "41.48",
      "expiration_date": "39.88",
      "expiration_date_text": "40.68",
      "catchcopy": "サウジアラビアリアル"
    },
    {
      "id": 24,
      "title": "AED",
      "copyright": "42.21",
      "expiration_date": "40.85",
      "expiration_date_text": "41.53",
      "catchcopy": "UAEディルハム"
    },
    {
      "id": 25,
      "title": "MXN",
      "copyright": "9.29",
      "expiration_date": "7.29",
      "expiration_date_text": "8.29",
      "catchcopy": "メキシコペソ"
    },
    {
      "id": 26,
      "title": "PGK",
      "copyright": "37.89",
      "expiration_date": "*****",
      "expiration_date_text": "37.39",
      "catchcopy": "パプアニューギニアキナ"
    },
    {
      "id": 27,
      "title": "HUF",
      "copyright": "0.48",
      "expiration_date": "0.44",
      "expiration_date_text": "0.46",
      "catchcopy": "ハンガリーフォリント"
    },
    {
      "id": 28,
      "title": "CZK",
      "copyright": "7.43",
      "expiration_date": "7.19",
      "expiration_date_text": "7.31",
      "catchcopy": "チェココロナ"
    },
    {
      "id": 29,
      "title": "PLN",
      "copyright": "43.18",
      "expiration_date": "40.78",
      "expiration_date_text": "41.98",
      "catchcopy": "ポーランドズロチ"
    },
    {
      "id": 30,
      "title": "TRY",
      "copyright": "5.44",
      "expiration_date": "1.84",
      "expiration_date_text": "3.64",
      "catchcopy": "トルコリラ"
    },
    {
      "id": 31,
      "title": "TWD",
      "copyright": "4.98",
      "expiration_date": "0",
      "expiration_date_text": "0",
      "catchcopy": "台湾ドル"
    },
    {
      "id": 32,
      "title": "KRW(100)",
      "copyright": "10.66",
      "expiration_date": "0",
      "expiration_date_text": "0",
      "catchcopy": "韓国ウォン"
    },
    {
      "id": 33,
      "title": "IDR(100)",
      "copyright": "0.92",
      "expiration_date": "0",
      "expiration_date_text": "0",
      "catchcopy": "インドネシアルピア"
    },
    {
      "id": 34,
      "title": "MYR",
      "copyright": "36.29",
      "expiration_date": "0",
      "expiration_date_text": "0",
      "catchcopy": "マレーシアリンギ"
    },
    {
      "id": 35,
      "title": "XPF",
      "copyright": "1.49",
      "expiration_date": "0",
      "expiration_date_text": "0",
      "catchcopy": "パシフィックフラン"
    },
    {
      "id": 36,
      "title": "BRL",
      "copyright": "28.38",
      "expiration_date": "0",
      "expiration_date_text": "0",
      "catchcopy": "ブラジルレアル"
    },
    {
      "id": 37,
      "title": "VND(100)",
      "copyright": "0.58",
      "expiration_date": "0",
      "expiration_date_text": "0",
      "catchcopy": "ベトナムドン"
    },
    {
      "id": 38,
      "title": "EGP",
      "copyright": "3.22",
      "expiration_date": "0",
      "expiration_date_text": "0",
      "catchcopy": "エジプトポンド"
    },
    {
      "id": 39,
      "title": "RUB",
      "copyright": "1.93",
      "expiration_date": "0",
      "expiration_date_text": "0",
      "catchcopy": "ロシアルーブル"
    }
  ]
}