{
  "purchase_comic": [
    {
      "id": 1,
      "title": "BTC/JPY",
      "copyright": "15,095,278円",
      "expiration_date": "-0.57%",
      "catchcopy": "ビットコイン"
    },
    {
      "id": 2,
      "title": "ETH/JPY",
      "copyright": "517,864円",
      "expiration_date": "-2.20%",
      "catchcopy": "イーサリアム"
    },
    {
      "id": 3,
      "title": "XRP/JPY",
      "copyright": "218.12円",
      "expiration_date": "-4.02%",
      "catchcopy": "リップル（XRP）"
    },
    {
      "id": 4,
      "title": "SHIB/JPY",
      "copyright": "0.0039367円",
      "expiration_date": "-3.06%",
      "catchcopy": "シバイヌ"
    },
    {
      "id": 5,
      "title": "POL/JPY",
      "copyright": "87.43円",
      "expiration_date": "-1.98%",
      "catchcopy": "ポリゴンエコシステムトークン"
    },
    {
      "id": 6,
      "title": "MATIC/JPY",
      "copyright": "87.27円",
      "expiration_date": "-2.24%",
      "catchcopy": "ポリゴン"
    },
    {
      "id": 7,
      "title": "DOGE/JPY",
      "copyright": "65.77円",
      "expiration_date": "-1.98%",
      "catchcopy": "ドージコイン"
    },
    {
      "id": 8,
      "title": "AVAX/JPY",
      "copyright": "6,475円",
      "expiration_date": "-1.51%",
      "catchcopy": "アバランチ"
    },
    {
      "id": 9,
      "title": "BCH/JPY",
      "copyright": "78,897円",
      "expiration_date": "-0.61%",
      "catchcopy": "ビットコインキャッシュ"
    },
    {
      "id": 10,
      "title": "DOT/JPY",
      "copyright": "1,347円",
      "expiration_date": "-6.98%",
      "catchcopy": "ポルカドット"
    },
    {
      "id": 11,
      "title": "LINK/JPY",
      "copyright": "2,784円",
      "expiration_date": "+1.38%",
      "catchcopy": "チェーンリンク"
    },
    {
      "id": 12,
      "title": "LTC/JPY",
      "copyright": "14,883円",
      "expiration_date": "-4.38%",
      "catchcopy": "ライトコイン"
    },
    {
      "id": 13,
      "title": "XLM/JPY",
      "copyright": "82.803円",
      "expiration_date": "+4.09%",
      "catchcopy": "ステラルーメン"
    },
    {
      "id": 14,
      "title": "ETC/JPY",
      "copyright": "4,419円",
      "expiration_date": "-4.80%",
      "catchcopy": "イーサリアムクラシック"
    },
    {
      "id": 15,
      "title": "MKR/JPY",
      "copyright": "267,893.11円",
      "expiration_date": "+3.28%",
      "catchcopy": "メイカー"
    },
    {
      "id": 16,
      "title": "IMX/JPY",
      "copyright": "269.2円",
      "expiration_date": "+7.34%",
      "catchcopy": "イミュータブル"
    },
    {
      "id": 17,
      "title": "RNDR/JPY",
      "copyright": "1,249.0円",
      "expiration_date": "+2.63%",
      "catchcopy": "レンダートークン"
    },
    {
      "id": 18,
      "title": "GRT/JPY",
      "copyright": "41.17円",
      "expiration_date": "+9.29%",
      "catchcopy": "ザ・グラフ"
    },
    {
      "id": 19,
      "title": "AXS/JPY",
      "copyright": "1,265円",
      "expiration_date": "+18.67%",
      "catchcopy": "アクシーインフィニティ"
    },
    {
      "id": 20,
      "title": "XTZ/JPY",
      "copyright": "209.9円",
      "expiration_date": "+17.20%",
      "catchcopy": "テゾス"
    },
    {
      "id": 21,
      "title": "FLR/JPY",
      "copyright": "3.658円",
      "expiration_date": "+1.75%",
      "catchcopy": "フレア"
    },
    {
      "id": 22,
      "title": "SAND/JPY",
      "copyright": "121.87円",
      "expiration_date": "+80.17%",
      "catchcopy": "ザ・サンドボックス"
    },
    {
      "id": 23,
      "title": "MANA/JPY",
      "copyright": "109.00円",
      "expiration_date": "+34.24%",
      "catchcopy": "ディセントラランド"
    },
    {
      "id": 24,
      "title": "CHZ/JPY",
      "copyright": "14.66円",
      "expiration_date": "+8.67%",
      "catchcopy": "チリーズ"
    },
    {
      "id": 25,
      "title": "APE/JPY",
      "copyright": "212.1円",
      "expiration_date": "+5.31%",
      "catchcopy": "エイプコイン"
    },
    {
      "id": 26,
      "title": "BAT/JPY",
      "copyright": "48.35円",
      "expiration_date": "+24.42%",
      "catchcopy": "ベーシックアテンショントークン"
    },
    {
      "id": 27,
      "title": "MASK/JPY",
      "copyright": "510.2円",
      "expiration_date": "+2.86%",
      "catchcopy": "マスクネットワーク"
    },
    {
      "id": 28,
      "title": "XEM/JPY",
      "copyright": "3.933円",
      "expiration_date": "+2.16%",
      "catchcopy": "ネム"
    },
    {
      "id": 29,
      "title": "LSK/JPY",
      "copyright": "181.9円",
      "expiration_date": "+6.75%",
      "catchcopy": "リスク"
    },
    {
      "id": 30,
      "title": "XYM/JPY",
      "copyright": "3.76円",
      "expiration_date": "+4.16%",
      "catchcopy": "シンボル"
    },
    {
      "id": 31,
      "title": "MONA/JPY",
      "copyright": "48.800円",
      "expiration_date": "-1.91%",
      "catchcopy": "モナコイン"
    },
    {
      "id": 32,
      "title": "PLT/JPY",
      "copyright": "6.00円",
      "expiration_date": "-3.85%",
      "catchcopy": "パレットトークン"
    },
    {
      "id": 33,
      "title": "DAI/JPY",
      "copyright": "153.9円",
      "expiration_date": "-0.58%",
      "catchcopy": "ダイ"
    },
    {
      "id": 34,
      "title": "ZPG/JPY",
      "copyright": "13,446.38円",
      "expiration_date": "-0.19%",
      "catchcopy": "ジパングコイン"
    },
    {
      "id": 35,
      "title": "ZPGAG/JPY",
      "copyright": "155.4円",
      "expiration_date": "0.00%",
      "catchcopy": "ジパングコインシルバー"
    },
    {
      "id": 36,
      "title": "ZPGPT/JPY",
      "copyright": "4,802円",
      "expiration_date": "+0.08%",
      "catchcopy": "ジパングコインプラチナ"
    }
  ]
}