[
  {
    "id": "TVC:GOLD",
    "symbol": "₩/g",
    "name": "금",
    "image": "https://raw.githubusercontent.com/bestapuri/Apuri/refs/heads/main/goldprice_kr/v2/goldicon.png",
    "current_price": 210853,
    "price_change_24h": 3120,
    "price_change_percentage_24h": 3120
  },
  {
    "id": "TVC:SILVER",
    "symbol": "₩/g",
    "name": "은",
    "image": "https://raw.githubusercontent.com/bestapuri/Apuri/refs/heads/main/goldprice_kr/v2/silvericon.png",
    "current_price": 2778,
    "price_change_24h": 114,
    "price_change_percentage_24h": 114
  },
  {
    "id": "TVC:PLATINUM",
    "symbol": "₩/g",
    "name": "백금",
    "image": "https://raw.githubusercontent.com/bestapuri/Apuri/refs/heads/main/goldprice_kr/v2/platinumicon.png",
    "current_price": 82400,
    "price_change_24h": 1867,
    "price_change_percentage_24h": 1867
  }
]